Metadata-Version: 1.0
Name: launchbox
Version: 0.1.1
Summary: Packaging and dependency resolution for chef-solo cookbooks
Home-page: http://github.com/RisingOak/launchbox
Author: Cosmin Stejerean
Author-email: cosmin@offbytwo.com
License: Apache License 2.0
Keywords: chef chef-solo dependency package bundle
Platform: UNKNOWN
Classifier: Development Status :: 3 - Alpha
Classifier: Environment :: Console
Classifier: License :: OSI Approved :: Apache Software License
Classifier: Topic :: System :: Software Distribution
Classifier: Topic :: Utilities
